examples/titanic/__init__.py
examples/titanic/run_tests.py
examples/titanic/setup_environment.py
trilogy_nlp/__init__.py
trilogy_nlp/config.py
trilogy_nlp/constants.py
trilogy_nlp/core.py
trilogy_nlp/enums.py
trilogy_nlp/environment.py
trilogy_nlp/exceptions.py
trilogy_nlp/helpers.py
trilogy_nlp/instrumentation.py
trilogy_nlp/main.py
trilogy_nlp/monkeypatch.py
trilogy_nlp/py.typed
trilogy_nlp/tools.py
trilogy_nlp/cache_providers/__init__.py
trilogy_nlp/cache_providers/base.py
trilogy_nlp/cache_providers/local_sqlite.py
trilogy_nlp/llm_interface/__init__.py
trilogy_nlp/llm_interface/constants.py
trilogy_nlp/llm_interface/examples.py
trilogy_nlp/llm_interface/models.py
trilogy_nlp/llm_interface/parsing.py
trilogy_nlp/llm_interface/tools.py
trilogy_nlp/llm_interface/validation.py
trilogy_nlp/prompts_v2/__init__.py
trilogy_nlp/prompts_v2/query_environment.py
trilogy_nlp/prompts_v2/query_system.py
trilogy_nlp/scripts/__init__.py
trilogy_nlp/scripts/main.py
pytrilogy_nlp-0.1.7.dist-info/LICENSE.md
pytrilogy_nlp-0.1.7.dist-info/METADATA
pytrilogy_nlp-0.1.7.dist-info/WHEEL
pytrilogy_nlp-0.1.7.dist-info/entry_points.txt
pytrilogy_nlp-0.1.7.dist-info/top_level.txt
pytrilogy_nlp-0.1.7.dist-info/RECORD
