Metadata-Version: 2.2
Name: pytrilogy-nlp
Version: 0.1.7
Summary: NLP interface for Trilogy
Home-page: 
Author: 
Author-email: pypreql-community@gmail.com
Classifier: Programming Language :: Python
Classifier: Programming Language :: Python :: 3
Classifier: Programming Language :: Python :: 3.9
Classifier: Programming Language :: Python :: 3.10
Classifier: Programming Language :: Python :: 3.11
Classifier: Programming Language :: Python :: 3.12
Classifier: Programming Language :: Python :: 3.13
License-File: LICENSE.md
Requires-Dist: pytrilogy<0.0.4.0,>=0.0.3.4
Requires-Dist: openai
Requires-Dist: langchain
Requires-Dist: langchain-community
Requires-Dist: langchain-openai
Requires-Dist: mediawikiapi
Requires-Dist: wikibase-rest-api-client
Requires-Dist: tomli-w
Provides-Extra: gemini
Requires-Dist: langchain-google-genai; extra == "gemini"
Provides-Extra: openai
Requires-Dist: langchain-openai; extra == "openai"
Provides-Extra: anthropic
Requires-Dist: langchain-anthropic; extra == "anthropic"
Dynamic: author-email
Dynamic: classifier
Dynamic: description
Dynamic: description-content-type
Dynamic: provides-extra
Dynamic: requires-dist
Dynamic: summary
